douze/__init__.py
douze/api.py
douze/idem_api.py
douze/models.py
douze/types.py
douze-0.1.8.dist-info/LICENSE
douze-0.1.8.dist-info/METADATA
douze-0.1.8.dist-info/WHEEL
douze-0.1.8.dist-info/RECORD
